<?xml version="1.0" encoding="UTF-8"?><!-- 7BKH1TE1 -->
<data>
<oSettings>
<sSpace>30</sSpace>
<rSpace>10</rSpace>
<url>www.isleronline.com</url>
<publisher>zkitap</publisher>
<uDate>2024-09-09 08:14:02</uDate>
<libraryId>20</libraryId>
</oSettings>
<categories>
<aCategory><cId>768</cId><cName>ALTYAPI YAYINLARI 2022-2023</cName></aCategory>
<aCategory><cId>840</cId><cName>AROMAT YAYINLARI</cName></aCategory>
<aCategory><cId>857</cId><cName>BİLGİ SARMAL 2024-2025</cName></aCategory>
<aCategory><cId>789</cId><cName>BİLGİ SARMAL 2023-2024</cName></aCategory>
<aCategory><cId>748</cId><cName>BİLGİ SARMAL 2022-2023</cName></aCategory>
<aCategory><cId>676</cId><cName>BİLGİ SARMAL 2021-2022</cName></aCategory>
<aCategory><cId>761</cId><cName>ÇAP YAYINLARI 2022-2023</cName></aCategory>
<aCategory><cId>474</cId><cName>Çap yayınları</cName></aCategory>
<aCategory><cId>711</cId><cName>VAF YAYINLARI</cName></aCategory>
<aCategory><cId>830</cId><cName>KRALLAR KARMASI YAYINLARI</cName></aCategory>
<aCategory><cId>457</cId><cName>ENS YAYINLARI</cName></aCategory>
<aCategory><cId>391</cId><cName>Hız ve Renk</cName></aCategory>
<aCategory><cId>124</cId><cName>Mrkz Yayınları</cName></aCategory>
<aCategory><cId>672</cId><cName>PES</cName></aCategory>
</categories><pics><pic><cId>474</cId><source>http://yeni.isleronline.com/uploads/set/6232d83965220.png</source><scale>135,189</scale><fileName>false</fileName><fileSize>0</fileSize><imageSize>60555</imageSize><vers>v_1</vers><fas>false</fas></pic>
<pic><cId>474</cId><source>http://yeni.isleronline.com/uploads/set/608680ba47d35.png</source><scale>135,189</scale><fileName>false</fileName><fileSize>0</fileSize><imageSize>47610</imageSize><vers>v_1</vers><fas>false</fas></pic>
<pic><cId>474</cId><source>http://yeni.isleronline.com/uploads/set/608686e10828a.png</source><scale>135,189</scale><fileName>false</fileName><fileSize>0</fileSize><imageSize>45836</imageSize><vers>v_1</vers><fas>false</fas></pic>
<pic><cId>676</cId><source>http://yeni.isleronline.com/uploads/set/61bb004b11368.png</source><scale>135,189</scale><fileName>false</fileName><fileSize>0</fileSize><imageSize>114415</imageSize><vers>v_1</vers><fas>false</fas></pic>
<pic><cId>711</cId><source>http://yeni.isleronline.com/uploads/set/633fd734177b7.png</source><scale>135,189</scale><fileName>false</fileName><fileSize>0</fileSize><imageSize>63826</imageSize><vers>v_1</vers><fas>false</fas></pic>
<pic><cId>711</cId><source>http://yeni.isleronline.com/uploads/set/633fc2e869f99.png</source><scale>135,189</scale><fileName>false</fileName><fileSize>0</fileSize><imageSize>70306</imageSize><vers>v_1</vers><fas>false</fas></pic>
<pic><cId>711</cId><source>http://yeni.isleronline.com/uploads/set/633fc1524f8ac.png</source><scale>135,189</scale><fileName>false</fileName><fileSize>0</fileSize><imageSize>80100</imageSize><vers>v_1</vers><fas>false</fas></pic>
<pic><cId>711</cId><source>http://yeni.isleronline.com/uploads/set/633d7eae16b6f.png</source><scale>135,189</scale><fileName>false</fileName><fileSize>0</fileSize><imageSize>71410</imageSize><vers>v_1</vers><fas>false</fas></pic>
<pic><cId>748</cId><source>http://yeni.isleronline.com/uploads/set/63c7890809098.png</source><scale>135,189</scale><fileName>false</fileName><fileSize>0</fileSize><imageSize>81392</imageSize><vers>v_1</vers><fas>false</fas></pic>
<pic><cId>748</cId><source>http://yeni.isleronline.com/uploads/set/63c7853ce56f9.png</source><scale>135,189</scale><fileName>false</fileName><fileSize>0</fileSize><imageSize>113660</imageSize><vers>v_1</vers><fas>false</fas></pic>
<pic><cId>789</cId><source>http://yeni.isleronline.com/uploads/set/65449306e8554.png</source><scale>135,189</scale><fileName>false</fileName><fileSize>0</fileSize><imageSize>114079</imageSize><vers>v_1</vers><fas>false</fas></pic>
<pic><cId>830</cId><source>http://yeni.isleronline.com/uploads/set/6593b55b49d34.png</source><scale>135,189</scale><fileName>false</fileName><fileSize>0</fileSize><imageSize>118831</imageSize><vers>v_1</vers><fas>false</fas></pic>
</pics>
</data>
